DynamicPointer.v
module dynamic_pointer (
    input clk,
    input reset,
    input load_dp,
    input inc_dp,  
    input write_dp, 
    input [15:0] dp_data_in,  
    output reg [15:0] dp_data_out 
);

always @(posedge clk or posedge reset) begin
    if (reset) begin
        dp_data_out <= 16'd0; 
    end else begin 
        if (load_dp) begin
            dp_data_out <= dp_data_in;
        end else if (inc_dp) begin
            dp_data_out <= dp_data_out + 16'd1; 
        end else if (write_dp) begin
            dp_data_out <= dp_data_in;
        end
    end
end

endmodule

testbenches/DynamicPointer_tb.v
`timescale 1ns/1ns
`include "DynamicPointer.v"

module dynamic_pointer_tb;

  reg clk;
  reg reset;
  reg load_dp;
  reg inc_dp;
  reg write_dp;
  reg [15:0] dp_data_in;
  wire [15:0] dp_data_out;

  dynamic_pointer dut (
    .clk(clk),
    .reset(reset),
    .load_dp(load_dp),
    .inc_dp(inc_dp),
    .write_dp(write_dp),
    .dp_data_in(dp_data_in),
    .dp_data_out(dp_data_out)
  );

  initial begin
    clk = 0;
    forever #5 clk = ~clk;
  end

  initial begin

    $dumpfile("dynamic_pointer_tb.vcd");
    $dumpvars(0, dynamic_pointer_tb);

    
    reset = 1;
    #10;
    reset = 0;

    load_dp = 1;
    dp_data_in = 16'h3800; 
    #10;
    load_dp = 0;

    inc_dp = 1;
    #10;
    inc_dp = 0;
    #10;
    inc_dp = 1;
    #10;
    inc_dp = 0;

    write_dp = 1;
    dp_data_in = 16'h5000;
    #10;
    write_dp = 0;

    #10;
    inc_dp = 1;
    #10; 
    inc_dp = 0; 

    #30;  
    
    $finish; 
  end

  always @(posedge clk) begin
    $display("Time: %d, clk: %b, reset: %b, load_dp: %b, inc_dp: %b, write_dp: %b, dp_data_in: %h, dp_data_out: %h",
              $time, clk, reset, load_dp, inc_dp, write_dp, dp_data_in, dp_data_out); 
  end

endmodule

dynamic_pointer_tb.vcd
$date
	Thu Mar 21 19:45:47 2024
$end
$version
	Icarus Verilog
$end
$timescale
	1ns
$end
$scope module dynamic_pointer_tb $end
$var wire 16 ! dp_data_out [15:0] $end
$var reg 1 " clk $end
$var reg 16 # dp_data_in [15:0] $end
$var reg 1 $ inc_dp $end
$var reg 1 % load_dp $end
$var reg 1 & reset $end
$var reg 1 ' write_dp $end
$scope module dut $end
$var wire 1 " clk $end
$var wire 16 ( dp_data_in [15:0] $end
$var wire 1 $ inc_dp $end
$var wire 1 % load_dp $end
$var wire 1 & reset $end
$var wire 1 ' write_dp $end
$var reg 16 ) dp_data_out [15:0] $end
$upscope $end
$upscope $end
$enddefinitions $end
$comment Show the parameter values. $end
$dumpall
$end
#0
$dumpvars
b0 )
bx (
x'
1&
x%
x$
bx #
0"
b0 !
$end
#5
1"
#10
0"
b11100000000000 #
b11100000000000 (
1%
0&
#15
b11100000000000 !
b11100000000000 )
1"
#20
0"
1$
0%
#25
b11100000000001 !
b11100000000001 )
1"
#30
0"
0$
#35
1"
#40
0"
1$
#45
b11100000000010 !
b11100000000010 )
1"
#50
0"
b101000000000000 #
b101000000000000 (
1'
0$
#55
b101000000000000 !
b101000000000000 )
1"
#60
0"
0'
#65
1"
#70
0"
1$
#75
b101000000000001 !
b101000000000001 )
1"
#80
0"
0$
