instruction_count_register.v
module instruction_count_register (
    input clk,
    input reset,
    input update_count,  
    output reg [15:0] count_out 
);

always @(posedge clk or posedge reset) begin
    if (reset) begin
        count_out <= 16'd0;
    end else if (update_count) begin
        count_out <= count_out + 16'd1;
    end
end

endmodule

instruction_count_register_tb.v
`timescale 1ns/1ns
`include "instruction_count_register.v"

module instruction_count_register_tb;

  reg clk;
  reg reset;
  reg update_count;
  wire [15:0] count_out;

  instruction_count_register dut (
    .clk(clk),
    .reset(reset),
    .update_count(update_count),
    .count_out(count_out)
  );

  initial begin
    clk = 0;
    forever #5 clk = ~clk;
  end

  initial begin
    $dumpfile("instruction_count_register_tb.vcd");
    $dumpvars(0, instruction_count_register_tb);
    reset = 1;
    #10;
    reset = 0; 

    update_count = 1;
    #10;
    update_count = 0;
    #10;
    update_count = 1;
    #20; 
    update_count = 0; 

    #50;

    update_count = 1;
    #10; 
    update_count = 0;

    $finish; 
  end

  always @(posedge clk) begin
    $display("Time: %d, clk: %b, reset: %b,  update_count: %b, count_out: %d",
              $time, clk, reset, update_count, count_out); 
  end

endmodule

instruction_count_register_tb.vcd
$date
	Thu Mar 21 19:45:47 2024
$end
$version
	Icarus Verilog
$end
$timescale
	1ns
$end
$scope module instruction_count_register_tb $end
$var wire 16 ! count_out [15:0] $end
$var reg 1 " clk $end
$var reg 1 # reset $end
$var reg 1 $ update_count $end
$scope module dut $end
$var wire 1 " clk $end
$var wire 1 # reset $end
$var wire 1 $ update_count $end
$var reg 16 % count_out [15:0] $end
$upscope $end
$upscope $end
$enddefinitions $end
$comment Show the parameter values. $end
$dumpall
$end
#0
$dumpvars
b0 %
x$
1#
0"
b0 !
$end
#5
1"
#10
0"
1$
0#
#15
b1 !
b1 %
1"
#20
0"
0$
#25
1"
#30
0"
1$
#35
b10 !
b10 %
1"
#40
0"
#45
b11 !
b11 %
1"
#50
0"
0$
#55
1"
#60
0"
#65
1"
#70
0"
#75
1"
#80
0"
#85
1"
#90
0"
#95
1"
#100
0"
1$
#105
b100 !
b100 %
1"
#110
0"
0$
