InstructionPointer.v
module instruction_pointer (
    input clk,
    input reset,
    input load_ip,
    input inc_ip,  
    input [15:0] ip_data_in,  
    output reg [15:0] ip_data_out 
);

always @(posedge clk or posedge reset) begin
    if (reset) begin
        ip_data_out <= 16'd0; 
    end else if (load_ip) begin
        ip_data_out <= ip_data_in;
    end else if (inc_ip) begin
        ip_data_out <= ip_data_out + 16'd1; 
    end
end

endmodule

InstructionPointer_tb.v
`timescale 1ns/1ns
`include "InstructionPointer.v"

module instruction_pointer_tb;

  reg clk;
  reg reset;
  reg load_ip;
  reg inc_ip;
  reg [15:0] ip_data_in;
  wire [15:0] ip_data_out;

  instruction_pointer dut (
    .clk(clk),
    .reset(reset),
    .load_ip(load_ip),
    .inc_ip(inc_ip),
    .ip_data_in(ip_data_in),
    .ip_data_out(ip_data_out)
  );

  initial begin
    clk = 0;
    forever #5 clk = ~clk; 
  end

  initial begin

    $dumpfile("instruction_pointer_tb.vcd");
    $dumpvars(0, instruction_pointer_tb);
    reset = 1; 
    #10; 
    reset = 0; 

    load_ip = 1;
    ip_data_in = 16'h1000; 
    #10;
    load_ip = 0;

    inc_ip = 1; 
    #10;
    inc_ip = 0; 
    #10; 
    inc_ip = 1;
    #10; 
    inc_ip = 0;

    load_ip = 1;
    ip_data_in = 16'h3500; 
    #10;
    load_ip = 0;

    #10; 
    inc_ip = 1; 
    #10; 
    inc_ip = 0;

    #30;  

    $finish; 
  end

  always @(posedge clk) begin
    $display("Time: %d, clk: %b, reset: %b, load_ip: %b, inc_ip: %b, ip_data_in: %h, ip_data_out: %h",
              $time, clk, reset, load_ip, inc_ip, ip_data_in, ip_data_out); 
  end

endmodule

instruction_pointer_tb.vcd
$date
	Thu Mar 21 19:45:47 2024
$end
$version
	Icarus Verilog
$end
$timescale
	1ns
$end
$scope module instruction_pointer_tb $end
$var wire 16 ! ip_data_out [15:0] $end
$var reg 1 " clk $end
$var reg 1 # inc_ip $end
$var reg 16 $ ip_data_in [15:0] $end
$var reg 1 % load_ip $end
$var reg 1 & reset $end
$scope module dut $end
$var wire 1 " clk $end
$var wire 1 # inc_ip $end
$var wire 16 ' ip_data_in [15:0] $end
$var wire 1 % load_ip $end
$var wire 1 & reset $end
$var reg 16 ( ip_data_out [15:0] $end
$upscope $end
$upscope $end
$enddefinitions $end
$comment Show the parameter values. $end
$dumpall
$end
#0
$dumpvars
b0 (
bx '
1&
x%
bx $
x#
0"
b0 !
$end
#5
1"
#10
0"
b1000000000000 $
b1000000000000 '
1%
0&
#15
b1000000000000 !
b1000000000000 (
1"
#20
0"
1#
0%
#25
b1000000000001 !
b1000000000001 (
1"
#30
0"
0#
#35
1"
#40
0"
1#
#45
b1000000000010 !
b1000000000010 (
1"
#50
0"
b11010100000000 $
b11010100000000 '
1%
0#
#55
b11010100000000 !
b11010100000000 (
1"
#60
0"
0%
#65
1"
#70
0"
1#
#75
b11010100000001 !
b11010100000001 (
1"
#80
0"
0#
