memory_correction_register.v
module memory_correction_register (
    input clk,
    input reset,
    input error_correction_event,  
    output reg [15:0] correction_count_out 
);

always @(posedge clk or posedge reset) begin
    if (reset) begin
        correction_count_out <= 16'd0;
    end else if (error_correction_event) begin
        correction_count_out <= correction_count_out + 16'd1;
    end
end

endmodule

memory_correction_register_tb.v
`timescale 1ns/1ns
`include "memory_correction_register.v"

module memory_correction_register_tb;

  reg clk;
  reg reset;
  reg error_correction_event;
  wire [15:0] correction_count_out;

  memory_correction_register dut (
    .clk(clk),
    .reset(reset),
    .error_correction_event(error_correction_event),
    .correction_count_out(correction_count_out)
  );

  initial begin
    clk = 0;
    forever #5 clk = ~clk; 
  end

  initial begin

    $dumpfile("memory_correction_register_tb.vcd");
    $dumpvars(0, memory_correction_register_tb);

    reset = 1;
    #10;
    reset = 0; 

    // Simulate a few correction events
    error_correction_event = 1;
    #10;
    error_correction_event = 0;
    #15; 
    error_correction_event = 1;
    #20; 
    error_correction_event = 0; 

    // Longer pause
    #50;

    // More infrequent events
    error_correction_event = 1; 
    #30;
    error_correction_event = 0;

    $finish; 
  end

  // Monitor signals
  always @(posedge clk) begin
    $display("Time: %d, clk: %b, reset: %b, error_correction_event: %b, correction_count_out: %d",
              $time, clk, reset, error_correction_event, correction_count_out); 
  end

endmodule

memory_correction_register_tb.vcd
$date
	Thu Mar 21 19:45:47 2024
$end
$version
	Icarus Verilog
$end
$timescale
	1ns
$end
$scope module memory_correction_register_tb $end
$var wire 16 ! correction_count_out [15:0] $end
$var reg 1 " clk $end
$var reg 1 # error_correction_event $end
$var reg 1 $ reset $end
$scope module dut $end
$var wire 1 " clk $end
$var wire 1 # error_correction_event $end
$var wire 1 $ reset $end
$var reg 16 % correction_count_out [15:0] $end
$upscope $end
$upscope $end
$enddefinitions $end
$comment Show the parameter values. $end
$dumpall
$end
#0
$dumpvars
b0 %
1$
x#
0"
b0 !
$end
#5
1"
#10
0"
1#
0$
#15
b1 !
b1 %
1"
#20
0"
0#
#25
1"
#30
0"
#35
b10 !
b10 %
1"
1#
#40
0"
#45
b11 !
b11 %
1"
#50
0"
#55
1"
0#
#60
0"
#65
1"
#70
0"
#75
1"
#80
0"
#85
1"
#90
0"
#95
1"
#100
0"
#105
b100 !
b100 %
1"
1#
#110
0"
#115
b101 !
b101 %
1"
#120
0"
#125
b110 !
b110 %
1"
#130
0"
#135
1"
0#
