modules/memory_access_register.v
module memory_access_register (
    input clk,
    input reset,
    input count_access,  
    output reg [15:0] access_count_out 
);

always @(posedge clk or posedge reset) begin
    if (reset) begin
        access_count_out <= 16'd0;
    end else if (count_access) begin
        access_count_out <= access_count_out + 16'd1;
    end
end

endmodule

testbenches/memory_access_register_tb.v
`timescale 1ns/1ns
`include "memory_access_register.v"

module memory_access_register_tb;

  reg clk;
  reg reset;
  reg count_access;
  wire [15:0] access_count_out;

  memory_access_register dut (
    .clk(clk),
    .reset(reset),
    .count_access(count_access),
    .access_count_out(access_count_out)
  );

  initial begin
    clk = 0;
    forever #5 clk = ~clk;
  end

  initial begin

    $dumpfile("memory_access_register_tb.vcd");
    $dumpvars(0, memory_access_register_tb);

    reset = 1;
    #10;
    reset = 0; 

    count_access = 1;
    #10;
    count_access = 0;
    #15; 
    count_access = 1;
    #10; 
    count_access = 0; 
    #5;
    count_access = 1;
    #10;
    #60;

    $finish; 
  end

  always @(posedge clk) begin
    $display("Time: %d, clk: %b, reset: %b, count_access: %b, access_count_out: %d",
              $time, clk, reset, count_access, access_count_out); 
  end

endmodule

memory_access_register_tb.vcd
$date
	Thu Mar 21 19:45:47 2024
$end
$version
	Icarus Verilog
$end
$timescale
	1ns
$end
$scope module memory_access_register_tb $end
$var wire 16 ! access_count_out [15:0] $end
$var reg 1 " clk $end
$var reg 1 # count_access $end
$var reg 1 $ reset $end
$scope module dut $end
$var wire 1 " clk $end
$var wire 1 # count_access $end
$var wire 1 $ reset $end
$var reg 16 % access_count_out [15:0] $end
$upscope $end
$upscope $end
$enddefinitions $end
$comment Show the parameter values. $end
$dumpall
$end
#0
$dumpvars
b0 %
1$
x#
0"
b0 !
$end
#5
1"
#10
0"
1#
0$
#15
b1 !
b1 %
1"
#20
0"
0#
#25
1"
#30
0"
#35
b10 !
b10 %
1"
1#
#40
0"
#45
1"
0#
#50
0"
1#
#55
b11 !
b11 %
1"
#60
0"
#65
b100 !
b100 %
1"
#70
0"
#75
b101 !
b101 %
1"
#80
0"
#85
b110 !
b110 %
1"
#90
0"
#95
b111 !
b111 %
1"
#100
0"
#105
b1000 !
b1000 %
1"
#110
0"
#115
b1001 !
b1001 %
1"
