StaticPointer.v
module static_pointer (
    input clk,
    input reset,
    input load_sp,
    input inc_sp,  
    input write_sp, 
    input [15:0] sp_data_in,  
    output reg [15:0] sp_data_out,
    output reg invalid_write  
);

always @(posedge clk or posedge reset) begin
    if (reset) begin
        sp_data_out <= 16'd0; 
        invalid_write <= 1'b0; 
    end else begin 
        if (load_sp) begin
            sp_data_out <= sp_data_in;
        end else if (inc_sp) begin
            sp_data_out <= sp_data_out + 16'd1; 
        end

        if (write_sp) begin
            invalid_write <= 1'b1; 
        end else begin
            invalid_write <= 1'b0;  
        end
    end
end

endmodule

StaticPointer_tb.v
`timescale 1ns/1ns
`include "StaticPointer.v"

module static_pointer_tb;

  reg clk;
  reg reset;
  reg load_sp;
  reg inc_sp;
  reg write_sp;
  reg [15:0] sp_data_in;
  wire [15:0] sp_data_out;
  wire invalid_write;

  static_pointer dut (
    .clk(clk),
    .reset(reset),
    .load_sp(load_sp),
    .inc_sp(inc_sp),
    .write_sp(write_sp),
    .sp_data_in(sp_data_in),
    .sp_data_out(sp_data_out),
    .invalid_write(invalid_write)
  );

  initial begin
    clk = 0;
    forever #5 clk = ~clk;
  end

  initial begin
    $dumpfile("static_pointer_tb.vcd");
    $dumpvars(0, static_pointer_tb);

    reset = 1;
    #10;
    reset = 0;

    load_sp = 1;
    sp_data_in = 16'h2800; 
    #10;
    load_sp = 0;

    inc_sp = 1;
    #10;
    inc_sp = 0;

    write_sp = 1;
    sp_data_in = 16'hABCD; 
    #10;
    write_sp = 0;

    load_sp = 1;
    sp_data_in = 16'h3200;
    #10;
    load_sp = 0;

    #50;

    $finish; 
  end

  always @(posedge clk) begin
    $display("Time: %d, clk: %b, reset: %b, load_sp: %b, inc_sp: %b, write_sp: %b, sp_data_in: %h, sp_data_out: %h, invalid_write: %b",
              $time, clk, reset, load_sp, inc_sp, write_sp, sp_data_in, sp_data_out, invalid_write); 
  end

endmodule

static_pointer_tb.vcd
$date
	Thu Mar 21 19:45:47 2024
$end
$version
	Icarus Verilog
$end
$timescale
	1ns
$end
$scope module static_pointer_tb $end
$var wire 16 ! sp_data_out [15:0] $end
$var wire 1 " invalid_write $end
$var reg 1 # clk $end
$var reg 1 $ inc_sp $end
$var reg 1 % load_sp $end
$var reg 1 & reset $end
$var reg 16 ' sp_data_in [15:0] $end
$var reg 1 ( write_sp $end
$scope module dut $end
$var wire 1 # clk $end
$var wire 1 $ inc_sp $end
$var wire 1 % load_sp $end
$var wire 1 & reset $end
$var wire 16 ) sp_data_in [15:0] $end
$var wire 1 ( write_sp $end
$var reg 1 " invalid_write $end
$var reg 16 * sp_data_out [15:0] $end
$upscope $end
$upscope $end
$enddefinitions $end
$comment Show the parameter values. $end
$dumpall
$end
#0
$dumpvars
b0 *
bx )
x(
bx '
1&
x%
x$
0#
0"
b0 !
$end
#5
1#
#10
0#
b10100000000000 '
b10100000000000 )
1%
0&
#15
b10100000000000 !
b10100000000000 *
1#
#20
0#
1$
0%
#25
b10100000000001 !
b10100000000001 *
1#
#30
0#
b1010101111001101 '
b1010101111001101 )
1(
0$
#35
1"
1#
#40
0#
b11001000000000 '
b11001000000000 )
1%
0(
#45
0"
b11001000000000 !
b11001000000000 *
1#
#50
0#
0%
